LICENSE
MANIFEST.in
README.rst
setup.cfg
setup.py
versioneer.py
scikit_surgerycalibration.egg-info/PKG-INFO
scikit_surgerycalibration.egg-info/SOURCES.txt
scikit_surgerycalibration.egg-info/dependency_links.txt
scikit_surgerycalibration.egg-info/entry_points.txt
scikit_surgerycalibration.egg-info/requires.txt
scikit_surgerycalibration.egg-info/top_level.txt
sksurgerycalibration/__init__.py
sksurgerycalibration/_version.py
sksurgerycalibration/algorithms/__init__.py
sksurgerycalibration/algorithms/pivot.py
sksurgerycalibration/algorithms/sphere_fitting.py
sksurgerycalibration/algorithms/triangulate.py
sksurgerycalibration/ui/__init__.py
sksurgerycalibration/ui/pivot_calibration_app.py
sksurgerycalibration/ui/pivot_calibration_command_line.py
sksurgerycalibration/video/__init__.py
sksurgerycalibration/video/quaternion_utils.py
sksurgerycalibration/video/video_calibration_cost_functions.py
sksurgerycalibration/video/video_calibration_data.py
sksurgerycalibration/video/video_calibration_driver_base.py
sksurgerycalibration/video/video_calibration_driver_mono.py
sksurgerycalibration/video/video_calibration_driver_stereo.py
sksurgerycalibration/video/video_calibration_hand_eye.py
sksurgerycalibration/video/video_calibration_io.py
sksurgerycalibration/video/video_calibration_metrics.py
sksurgerycalibration/video/video_calibration_params.py
sksurgerycalibration/video/video_calibration_utils.py
sksurgerycalibration/video/video_calibration_wrapper.py
tests/test_requirements.py
tests/algorithms/__init__.py
tests/algorithms/test_pivot.py
tests/algorithms/test_sphere_fitting.py
tests/algorithms/test_triangulate.py
tests/ui/__init__.py
tests/ui/test_pivot_calibration.py
tests/video/__init__.py
tests/video/test_charuco_plus_chessboard.py
tests/video/test_chessboard_calibration.py
tests/video/test_data_param_io.py
tests/video/test_hand_eye.py
tests/video/test_handeye_dots.py
tests/video/test_iterative.py
tests/video/test_load_calib_utils.py
tests/video/test_precalib.py
tests/video/test_video_calibration.py
tests/video/video_testing_utils.py