Metadata-Version: 2.4
Name: scikit-surgerycalibration
Version: 1.2.0
Summary: scikit-surgerycalibration provides algorithms designed for the calibration of surgical instruments
Home-page: https://github.com/SciKit-Surgery/scikit-surgerycalibration 
Author: Stephen Thompson
Author-email: s.thompson@ucl.ac.uk
License: BSD-3 license
Keywords: medical imaging
Classifier: Development Status :: 3 - Alpha
Classifier: Intended Audience :: Developers
Classifier: Intended Audience :: Healthcare Industry
Classifier: Intended Audience :: Information Technology
Classifier: Intended Audience :: Science/Research
Classifier: License :: OSI Approved :: BSD License
Classifier: Programming Language :: Python
Classifier: Programming Language :: Python :: 2
Classifier: Programming Language :: Python :: 3
Classifier: Topic :: Scientific/Engineering :: Information Analysis
Classifier: Topic :: Scientific/Engineering :: Medical Science Apps.
License-File: LICENSE
Requires-Dist: numpy>=2.0.0
Requires-Dist: ipykernel
Requires-Dist: nbsphinx
Requires-Dist: scipy
Requires-Dist: opencv-contrib-python-headless>=4.10.0.84
Requires-Dist: scikit-surgerycore
Requires-Dist: scikit-surgeryimage>=1.0.0
Dynamic: author
Dynamic: author-email
Dynamic: classifier
Dynamic: description
Dynamic: description-content-type
Dynamic: home-page
Dynamic: keywords
Dynamic: license
Dynamic: license-file
Dynamic: requires-dist
Dynamic: summary
